{
  "users": [
    {
      "id": 1,
      "name": "Vlad",
      "age": 20,
      "sex": "male",
      "experience": [
        1
      ]
    },
    {
      "id": 20,
      "name": "Vlad",
      "age": 40,
      "sex": "male",
      "experience": [
        1
      ]
    },
    {
      "id": 2,
      "name": "Slava",
      "age": 30,
      "sex": "male",
      "experience": [
        3,
        2,
        4,
        1
      ]
    },
    {
      "id": 3,
      "name": "Yura",
      "age": 30,
      "sex": "male",
      "experience": [
        3,
        1
      ]
    },
    {
      "id": 4,
      "name": "Elena",
      "age": 25,
      "sex": "female"
    },
    {
      "name": "papi4",
      "age": "44",
      "sex": "male",
      "experience": [
        "1",
        "2"
      ],
      "id": 23
    }
  ],
  "companies": [
    {
      "id": 2,
      "title": "TM"
    },
    {
      "id": 1,
      "title": "GL"
    },
    {
      "id": 3,
      "title": "Nexteum"
    },
    {
      "id": 4,
      "title": "Niko-tech"
    }
  ],
  "signIns": [
    {
      "id": 1,
      "login": "Vlad",
      "password": "1234"
    },
    {
      "id": 2,
      "login": "Slava",
      "password": "1234"
    },
    {
      "login": "Denis",
      "password": "den22",
      "id": 3
    },
    {
      "login": "Katya",
      "password": "ld123",
      "id": 4
    }
  ]
}